app.py
demo_stretch_robot.py
demo_vigem_latch.py
assets/ClusteringWindowIcon.png
assets/FittsGridWindowIcon.png
assets/FittsTargetIcon.png
assets/MarkerButtonsWindowIcon.png
assets/MindRoveLogo.png
assets/ModelInteractorIcon.png
assets/NML_logo.png
assets/ScopeBackground.png
assets/SerialCrossHairIcon.png
assets/SpikeScope.png
assets/__init__.py
assets/cmu-scotty-scarf.png
assets/cmu-tartan-wave-gray-crop-01.png
assets/emg_00.png
assets/nml-official_banner__blown-up.png
assets/outline_desktop_windows_black_24dp.png
assets/outline_flash_on_black_24dp.png
assets/outline_live_tv_black_24dp.png
assets/record-player.png
assets/stream-network.ico
assets/xbox-controller.png
configurations/__init__.py
configurations/board_manager_config.xml
lib/__init__.py
lib/vigem_gamepad.dll
lib/vigem_gamepad.lib
nml/__init__.py
nml/_version.py
nml/application.py
nml/binary_logger.py
nml/binary_reader.py
nml/board_manager.py
nml/board_modes.py
nml/clickable_viewbox.py
nml/cluster_selection_window.py
nml/decoder.py
nml/direction_prompt_game.py
nml/emgdecomp_viz.py
nml/feature_weights.py
nml/fitts_grid_window.py
nml/frequency_buffer.py
nml/game_text.py
nml/ghost_enemy.py
nml/goal_circle.py
nml/grid.py
nml/gui_window.py
nml/hooks.py
nml/keybinds.py
nml/local_paths.py
nml/marker_buttons_gui_panel.py
nml/maze_generator.py
nml/model_interactor.py
nml/pacman_game.py
nml/pacman_level.py
nml/pacman_player.py
nml/priors.py
nml/processor.py
nml/processor_modes.py
nml/realtime_plotter.py
nml/ring_buffer.py
nml/serial_plot_window.py
nml/spike_logger.py
nml/spike_reader.py
nml/spike_scope.py
nml/stimulator_window.py
nml/stream_manager.py
nml/teensy.py
nml/utilities.py
nml/vigem.py
nml/vigemviz.py
nml/connections/__init__.py
nml/connections/parameter_socket.py
nml/connections/parser.py
nml/connections/stream_socket.py
nml/connections/tcp.py
nml/connections/ws.py
nml/driver/stimulator.py
nml/peripherals/__init__.py
nml/peripherals/gamepad_controller.py
nml/peripherals/robot_lsl_handler.py
nml_wtf_mindrove-1.0.3.dist-info/METADATA
nml_wtf_mindrove-1.0.3.dist-info/WHEEL
nml_wtf_mindrove-1.0.3.dist-info/entry_points.txt
nml_wtf_mindrove-1.0.3.dist-info/top_level.txt
nml_wtf_mindrove-1.0.3.dist-info/RECORD
