Metadata-Version: 2.4
Name: nml_wtf_mindrove
Version: 1.0.3
Summary: NML MindRove EMG tools, GUI apps, real-time decoding, and vendored MindRove Python drivers.
Author-email: "Neuro-Mechatronics Interfaces (NML)" <info@nml.wtf>
License: MIT
Project-URL: Homepage, https://github.com/Neuro-Mechatronics-Interfaces/MindRove-EMG
Project-URL: Repository, https://github.com/Neuro-Mechatronics-Interfaces/MindRove-EMG
Classifier: Programming Language :: Python :: 3
Classifier: Programming Language :: Python :: 3 :: Only
Classifier: License :: OSI Approved :: MIT License
Classifier: Operating System :: OS Independent
Classifier: Topic :: Scientific/Engineering
Classifier: Topic :: System :: Hardware :: Universal Serial Bus (USB)
Classifier: Intended Audience :: Science/Research
Classifier: Development Status :: 3 - Alpha
Requires-Python: >=3.10
Requires-Dist: PyQt5==5.15.7
Requires-Dist: PyQt5-Qt5==5.15.2
Requires-Dist: PyQt5-sip==12.11.0
Requires-Dist: pyqtgraph==0.12.4
Requires-Dist: numba==0.61.0
Requires-Dist: numpy==1.26.4
Requires-Dist: nptyping==2.5.0
Requires-Dist: matplotlib==3.9.2
Requires-Dist: mindrove==5.2.3
Requires-Dist: scipy==1.14.1
Requires-Dist: scikit-learn==1.5.2
Requires-Dist: hidapi==0.14.0.post4
Requires-Dist: colorama==0.4.6
Requires-Dist: contourpy==1.3.0
Requires-Dist: cycler==0.12.1
Requires-Dist: joblib==1.4.2
Requires-Dist: keyboard==0.13.5
Requires-Dist: kiwisolver==1.4.7
Requires-Dist: llvmlite==0.44.0
Requires-Dist: pandas==2.2.3
Requires-Dist: pillow==11.0.0
Requires-Dist: pyserial==3.5
Requires-Dist: pluggy==1.5.0
Requires-Dist: psutil==7.0.0
Requires-Dist: pytest==8.3.4
Requires-Dist: python-dateutil==2.9.0.post0
Requires-Dist: pylsl==1.17.6
Requires-Dist: pynput==1.8.1
Requires-Dist: pyparsing==3.2.0
Requires-Dist: six==1.16.0
Requires-Dist: threadpoolctl==3.5.0
Requires-Dist: typish==1.9.3
Requires-Dist: tzdata==2024.2
Requires-Dist: websockets==15.0
Provides-Extra: dev
Requires-Dist: pytest; extra == "dev"
Requires-Dist: black; extra == "dev"
Requires-Dist: mypy; extra == "dev"
Requires-Dist: ruff; extra == "dev"
